lektor_scsscompile.py
lektor_scsscompile-1.3.0.dist-info/LICENSE
lektor_scsscompile-1.3.0.dist-info/METADATA
lektor_scsscompile-1.3.0.dist-info/WHEEL
lektor_scsscompile-1.3.0.dist-info/entry_points.txt
lektor_scsscompile-1.3.0.dist-info/top_level.txt
lektor_scsscompile-1.3.0.dist-info/RECORD
