Metadata-Version: 2.1
Name: lektor-scsscompile
Version: 1.3.0
Summary: SASS compiler for Lektor, thats based on libsass.
Home-page: https://github.com/maxbachmann/lektor-SCSScompile
Author: maxbachmann
Author-email: kontakt@maxbachmann.de
License: MIT
Keywords: Lektor plugin
Platform: UNKNOWN
Classifier: Development Status :: 5 - Production/Stable
Classifier: Framework :: Lektor
Classifier: Environment :: Plugins
Classifier: Intended Audience :: Developers
Classifier: License :: OSI Approved :: MIT License
Classifier: Programming Language :: Python :: 3
Requires-Dist: libsass
Requires-Dist: termcolor
